{
  "hash": "1c425576eff75f8937cc3c23abef10b1",
  "result": {
    "markdown": "---\ntitle: Bombus nevadensis\nsubtite: Nevada bumblebee\nengine: knitr\ncategories:\n  - Apidae\nfreeze: auto\ndescription:  <span class=\"sh-badge\">SH list</span> <span class=\"pe-badge\">PM Evidence</span>\n---\n\n![©️ stjayaaa.](https://inaturalist-open-data.s3.amazonaws.com/photos/310253992/medium.jpg){height=300}\n\n\n\n\n\n\n::: {.cell}\n::: {.cell-output-display}\n```{=html}\n<div class=\"plotly html-widget html-fill-item-overflow-hidden html-fill-item\" id=\"htmlwidget-7225d7da58261dff7771\" style=\"width:100%;height:464px;\"></div>\n<script type=\"application/json\" data-for=\"htmlwidget-7225d7da58261dff7771\">{\"x\":{\"visdat\":{\"3d384a1730fc\":[\"function () \",\"plotlyVisDat\"]},\"cur_data\":\"3d384a1730fc\",\"attrs\":{\"3d384a1730fc\":{\"alpha_stroke\":1,\"sizes\":[10,100],\"spans\":[1,20],\"lat\":{},\"lon\":{},\"mode\":\"markers\",\"type\":\"scattermapbox\",\"color\":{},\"text\":{},\"size\":10,\"name\":\"\",\"inherit\":true}},\"layout\":{\"margin\":{\"b\":40,\"l\":60,\"t\":25,\"r\":10},\"hovermode\":\"closest\",\"showlegend\":false,\"legend\":{\"yanchor\":\"top\",\"y\":0.5},\"mapbox\":{\"style\":\"carto-positron\",\"show_legend\":true,\"zoom\":3.7999999999999998,\"center\":{\"lon\":-127,\"lat\":50}},\"title\":\"GBIF observations in the Pacific Maritime region\"},\"source\":\"A\",\"config\":{\"modeBarButtonsToAdd\":[\"hoverclosest\",\"hovercompare\"],\"showSendToCloud\":false},\"data\":[{\"lat\":[49.094673,49.249448999999998,49.243324999999999,49.173563000000001,49.243324999999999,48.447920000000003,49.068303999999998,49.125774,49.06156,49.227378000000002,49.238605,48.5625,49.510219999999997,49.063296999999999,49.122556000000003,49.238633,49.227232999999998,49.229188000000001,49.229190000000003,49.240485999999997,49.230933999999998,49.068272,49.276451999999999,48.997539000000003,48.997539000000003,49.200000000000003,48.997539000000003,49.200000000000003],\"lon\":[-123.08323799999999,-123.236853,-123.10445199999999,-123.099131,-123.10445199999999,-123.46769399999999,-123.150884,-123.197169,-123.097159,-123.046967,-123.12603900000001,-123.508932,-123.600847,-123.15494700000001,-123.059022,-123.12580800000001,-123.0458,-123.084875,-123.084727,-123.101472,-123.085007,-123.152147,-124.189449,-123.680847,-123.680847,-124.016667,-123.680847,-124.016667],\"mode\":\"markers\",\"type\":\"scattermapbox\",\"text\":[\"Species: Bombus nevadensis <br />Observed: July 15, 2023\",\"Species: Bombus nevadensis <br />Observed: May 18, 2023\",\"Species: Bombus nevadensis <br />Observed: July 11, 2021\",\"Species: Bombus nevadensis <br />Observed: July 07, 2023\",\"Species: Bombus nevadensis <br />Observed: July 22, 2021\",\"Species: Bombus nevadensis <br />Observed: July 28, 2023\",\"Species: Bombus nevadensis <br />Observed: July 20, 2023\",\"Species: Bombus nevadensis <br />Observed: July 22, 2023\",\"Species: Bombus nevadensis <br />Observed: June 28, 2023\",\"Species: Bombus nevadensis <br />Observed: June 08, 2023\",\"Species: Bombus nevadensis <br />Observed: June 06, 2023\",\"Species: Bombus nevadensis <br />Observed: May 13, 2023\",\"Species: Bombus nevadensis <br />Observed: August 24, 2022\",\"Species: Bombus nevadensis <br />Observed: August 07, 2022\",\"Species: Bombus nevadensis <br />Observed: July 01, 2022\",\"Species: Bombus nevadensis <br />Observed: June 01, 2022\",\"Species: Bombus nevadensis <br />Observed: July 29, 2021\",\"Species: Bombus nevadensis <br />Observed: July 22, 2021\",\"Species: Bombus nevadensis <br />Observed: July 22, 2021\",\"Species: Bombus nevadensis <br />Observed: July 12, 2021\",\"Species: Bombus nevadensis <br />Observed: May 29, 2021\",\"Species: Bombus nevadensis <br />Observed: July 18, 2020\",\"Species: Bombus nevadensis <br />Observed: May 20, 1954\",\"Species: Bombus nevadensis <br />Observed: July 22, 1965\",\"Species: Bombus nevadensis <br />Observed: July 22, 1965\",\"Species: Bombus nevadensis <br />Observed: July 21, 1959\",\"Species: Bombus nevadensis <br />Observed: July 15, 1967\",\"Species: Bombus nevadensis <br />Observed: September 01, 1962\"],\"marker\":{\"colorbar\":{\"title\":\"Year\",\"ticklen\":2},\"cmin\":1954,\"cmax\":2023,\"colorscale\":[[\"0\",\"rgba(68,1,84,1)\"],[\"0.0416666666666667\",\"rgba(70,19,97,1)\"],[\"0.0833333333333333\",\"rgba(72,32,111,1)\"],[\"0.125\",\"rgba(71,45,122,1)\"],[\"0.166666666666667\",\"rgba(68,58,128,1)\"],[\"0.208333333333333\",\"rgba(64,70,135,1)\"],[\"0.25\",\"rgba(60,82,138,1)\"],[\"0.291666666666667\",\"rgba(56,93,140,1)\"],[\"0.333333333333333\",\"rgba(49,104,142,1)\"],[\"0.375\",\"rgba(46,114,142,1)\"],[\"0.416666666666667\",\"rgba(42,123,142,1)\"],[\"0.458333333333333\",\"rgba(38,133,141,1)\"],[\"0.5\",\"rgba(37,144,140,1)\"],[\"0.541666666666667\",\"rgba(33,154,138,1)\"],[\"0.583333333333333\",\"rgba(39,164,133,1)\"],[\"0.625\",\"rgba(47,174,127,1)\"],[\"0.666666666666667\",\"rgba(53,183,121,1)\"],[\"0.708333333333333\",\"rgba(79,191,110,1)\"],[\"0.75\",\"rgba(98,199,98,1)\"],[\"0.791666666666667\",\"rgba(119,207,85,1)\"],[\"0.833333333333333\",\"rgba(147,214,70,1)\"],[\"0.875\",\"rgba(172,220,52,1)\"],[\"0.916666666666667\",\"rgba(199,225,42,1)\"],[\"0.958333333333333\",\"rgba(226,228,40,1)\"],[\"1\",\"rgba(253,231,37,1)\"]],\"showscale\":false,\"color\":[2023,2023,2021,2023,2021,2023,2023,2023,2023,2023,2023,2023,2022,2022,2022,2022,2021,2021,2021,2021,2021,2020,1954,1965,1965,1959,1967,1962],\"size\":[55,55,55,55,55,55,55,55,55,55,55,55,55,55,55,55,55,55,55,55,55,55,55,55,55,55,55,55],\"sizemode\":\"area\",\"line\":{\"colorbar\":{\"title\":\"\",\"ticklen\":2},\"cmin\":1954,\"cmax\":2023,\"colorscale\":[[\"0\",\"rgba(68,1,84,1)\"],[\"0.0416666666666667\",\"rgba(70,19,97,1)\"],[\"0.0833333333333333\",\"rgba(72,32,111,1)\"],[\"0.125\",\"rgba(71,45,122,1)\"],[\"0.166666666666667\",\"rgba(68,58,128,1)\"],[\"0.208333333333333\",\"rgba(64,70,135,1)\"],[\"0.25\",\"rgba(60,82,138,1)\"],[\"0.291666666666667\",\"rgba(56,93,140,1)\"],[\"0.333333333333333\",\"rgba(49,104,142,1)\"],[\"0.375\",\"rgba(46,114,142,1)\"],[\"0.416666666666667\",\"rgba(42,123,142,1)\"],[\"0.458333333333333\",\"rgba(38,133,141,1)\"],[\"0.5\",\"rgba(37,144,140,1)\"],[\"0.541666666666667\",\"rgba(33,154,138,1)\"],[\"0.583333333333333\",\"rgba(39,164,133,1)\"],[\"0.625\",\"rgba(47,174,127,1)\"],[\"0.666666666666667\",\"rgba(53,183,121,1)\"],[\"0.708333333333333\",\"rgba(79,191,110,1)\"],[\"0.75\",\"rgba(98,199,98,1)\"],[\"0.791666666666667\",\"rgba(119,207,85,1)\"],[\"0.833333333333333\",\"rgba(147,214,70,1)\"],[\"0.875\",\"rgba(172,220,52,1)\"],[\"0.916666666666667\",\"rgba(199,225,42,1)\"],[\"0.958333333333333\",\"rgba(226,228,40,1)\"],[\"1\",\"rgba(253,231,37,1)\"]],\"showscale\":false,\"color\":[2023,2023,2021,2023,2021,2023,2023,2023,2023,2023,2023,2023,2022,2022,2022,2022,2021,2021,2021,2021,2021,2020,1954,1965,1965,1959,1967,1962]}},\"textfont\":{\"size\":55},\"line\":{\"width\":55},\"frame\":null},{\"type\":\"scattermapbox\",\"mode\":\"markers\",\"opacity\":0,\"hoverinfo\":\"none\",\"showlegend\":false,\"marker\":{\"colorbar\":{\"title\":\"Year\",\"ticklen\":2,\"len\":0.5,\"lenmode\":\"fraction\",\"y\":1,\"yanchor\":\"top\",\"dtick\":1},\"cmin\":1954,\"cmax\":2023,\"colorscale\":[[\"0\",\"rgba(68,1,84,1)\"],[\"0.0416666666666667\",\"rgba(70,19,97,1)\"],[\"0.0833333333333333\",\"rgba(72,32,111,1)\"],[\"0.125\",\"rgba(71,45,122,1)\"],[\"0.166666666666667\",\"rgba(68,58,128,1)\"],[\"0.208333333333333\",\"rgba(64,70,135,1)\"],[\"0.25\",\"rgba(60,82,138,1)\"],[\"0.291666666666667\",\"rgba(56,93,140,1)\"],[\"0.333333333333333\",\"rgba(49,104,142,1)\"],[\"0.375\",\"rgba(46,114,142,1)\"],[\"0.416666666666667\",\"rgba(42,123,142,1)\"],[\"0.458333333333333\",\"rgba(38,133,141,1)\"],[\"0.5\",\"rgba(37,144,140,1)\"],[\"0.541666666666667\",\"rgba(33,154,138,1)\"],[\"0.583333333333333\",\"rgba(39,164,133,1)\"],[\"0.625\",\"rgba(47,174,127,1)\"],[\"0.666666666666667\",\"rgba(53,183,121,1)\"],[\"0.708333333333333\",\"rgba(79,191,110,1)\"],[\"0.75\",\"rgba(98,199,98,1)\"],[\"0.791666666666667\",\"rgba(119,207,85,1)\"],[\"0.833333333333333\",\"rgba(147,214,70,1)\"],[\"0.875\",\"rgba(172,220,52,1)\"],[\"0.916666666666667\",\"rgba(199,225,42,1)\"],[\"0.958333333333333\",\"rgba(226,228,40,1)\"],[\"1\",\"rgba(253,231,37,1)\"]],\"showscale\":true,\"color\":[1954,2023],\"line\":{\"color\":\"rgba(255,127,14,1)\"}},\"lat\":[null,null],\"lon\":[null,null],\"frame\":null}],\"highlight\":{\"on\":\"plotly_click\",\"persistent\":false,\"dynamic\":false,\"selectize\":false,\"opacityDim\":0.20000000000000001,\"selected\":{\"opacity\":1},\"debounce\":0},\"shinyEvents\":[\"plotly_hover\",\"plotly_click\",\"plotly_selected\",\"plotly_relayout\",\"plotly_brushed\",\"plotly_brushing\",\"plotly_clickannotation\",\"plotly_doubleclick\",\"plotly_deselect\",\"plotly_afterplot\",\"plotly_sunburstclick\"],\"base_url\":\"https://plot.ly\"},\"evals\":[],\"jsHooks\":[]}</script>\n```\n:::\n:::\n\n<br><br>\n<center>\n\n\n<a href=\"https://inaturalist.ca/observations?place_id=7085&subview=map&taxon_id=341001\"><button type=\"button\" class=\"btn btn-secondary\">See all Bombus nevadensis in BC <i class=\"fa-solid fa-arrow-up-right-from-square\"></i> </button></a>\n</center>\n",
    "supporting": [],
    "filters": [
      "rmarkdown/pagebreak.lua"
    ],
    "includes": {
      "include-in-header": [
        "<script src=\"../../site_libs/htmlwidgets-1.6.2/htmlwidgets.js\"></script>\r\n<script src=\"../../site_libs/plotly-binding-4.10.3/plotly.js\"></script>\r\n<script src=\"../../site_libs/typedarray-0.1/typedarray.min.js\"></script>\r\n<script src=\"../../site_libs/jquery-3.5.1/jquery.min.js\"></script>\r\n<link href=\"../../site_libs/crosstalk-1.2.0/css/crosstalk.min.css\" rel=\"stylesheet\" />\r\n<script src=\"../../site_libs/crosstalk-1.2.0/js/crosstalk.min.js\"></script>\r\n<link href=\"../../site_libs/plotly-htmlwidgets-css-2.11.1/plotly-htmlwidgets.css\" rel=\"stylesheet\" />\r\n<script src=\"../../site_libs/plotly-main-2.11.1/plotly-latest.min.js\"></script>\r\n"
      ]
    },
    "engineDependencies": {},
    "preserve": {},
    "postProcess": true
  }
}